pycmtensor/__init__.py
pycmtensor/dataset.py
pycmtensor/defaultconfig.py
pycmtensor/expressions.py
pycmtensor/functions.py
pycmtensor/logger.py
pycmtensor/models/MNL.py
pycmtensor/models/ResLogit.py
pycmtensor/models/TasteNet.py
pycmtensor/models/__init__.py
pycmtensor/models/basic.py
pycmtensor/models/layers.py
pycmtensor/optimizers.py
pycmtensor/regularizers.py
pycmtensor/results.py
pycmtensor/run.py
pycmtensor/scheduler.py
pycmtensor/statistics.py
pycmtensor/utils.py
pycmtensor-1.14.2.dist-info/LICENSE
pycmtensor-1.14.2.dist-info/METADATA
pycmtensor-1.14.2.dist-info/WHEEL
pycmtensor-1.14.2.dist-info/RECORD
