Metadata-Version: 2.1
Name: pycmtensor
Version: 1.14.2
Summary: A robust and efficient Python package leveraging tensor computations for advanced discrete choice modelling.
Home-page: https://github.com/mwong009/pycmtensor
License: MIT
Keywords: tensor,discrete choice modelling,transportation,economics,python,data analysis,machine learning,artificial intelligence,scientific computing
Author: Melvin Wong
Requires-Python: >=3.9,<3.13
Classifier: Development Status :: 4 - Beta
Classifier: Intended Audience :: Developers
Classifier: Intended Audience :: Science/Research
Classifier: License :: OSI Approved :: MIT License
Classifier: Natural Language :: English
Classifier: Operating System :: OS Independent
Classifier: Programming Language :: Python :: 3
Classifier: Programming Language :: Python :: 3.9
Classifier: Programming Language :: Python :: 3.10
Classifier: Programming Language :: Python :: 3.11
Classifier: Topic :: Scientific/Engineering :: Artificial Intelligence
Requires-Dist: aesara (==2.9.3)
Requires-Dist: numpy (<1.26.0)
Requires-Dist: pandas (<2.1.0)
Requires-Dist: scikit-learn (<1.6.0)
Requires-Dist: scipy (<1.12.0)
Requires-Dist: seaborn (<0.14.0)
Project-URL: Repository, https://github.com/mwong009/pycmtensor
